{
  "green_cells": [],
  "blue_cells": [],
  "other_colors": [
    {
      "cell": "A1",
      "value": "CFF Mat",
      "color": "00000000"
    },
    {
      "cell": "B1",
      "value": "CFF Energy",
      "color": "00000000"
    },
    {
      "cell": "C1",
      "value": "CFF Disposal",
      "color": "00000000"
    },
    {
      "cell": "D1",
      "value": "CFF Total",
      "color": "00000000"
    },
    {
      "cell": "A2",
      "value": "=(((1-$L$17)*$L$15)+$L$17*(($L$10*SUM(EngS_BioCalc!C23:C24)+((1-$L$10)*$L$15)*(VLOOKUP(EngS_BioCalc!E33,'Dados auxiliares'!B7:H12,3,0)/VLOOKUP(EngS_BioCalc!E33,'Dados auxiliares'!B7:H12,7,0)))+((1-$L$10)*$L$18*($L$14-(SUM(EngS_BioCalc!C23:C24)*($L$22/VLOOKUP(EngS_BioCalc!E33,'Dados auxiliares'!B7:H12,3,0)))))))",
      "color": "00000000"
    },
    {
      "cell": "B2",
      "value": "=((1-$L$24)*$L$25)*((EngS_BioCalc!C21-VLOOKUP(EngS_BioCalc!E33,'Dados auxiliares'!B7:H12,7,0)*$L$29)*(EngS_BioCalc!E53+EngS_BioCalc!E40+EngS_BioCalc!C24))",
      "color": "00000000"
    },
    {
      "cell": "C2",
      "value": "=(1-$L$18-$L$25)*($L$11*(VLOOKUP(EngS_BioCalc!E33,'Dados auxiliares'!B7:H12,7,0)))",
      "color": "00000000"
    },
    {
      "cell": "D2",
      "value": "=SUM(A2:C2)+EngS_BioCalc!C21",
      "color": "00000000"
    },
    {
      "cell": "A4",
      "value": "Material",
      "color": "00000000"
    },
    {
      "cell": "B4",
      "value": "(1-R1) x Ev + R1 x (A x Erin + (1-A) x Ev x Qsin/Qp) + (1-A) x R2 x (Eout - Ev* x (QSout/QP)",
      "color": "00000000"
    },
    {
      "cell": "A5",
      "value": "Energy",
      "color": "00000000"
    },
    {
      "cell": "B5",
      "value": "(1-B) x R3 x (Eer - LHV x Xerheat x Eseheat - LHV x Xerelec x Eseelec)",
      "color": "00000000"
    },
    {
      "cell": "A6",
      "value": "Disposal",
      "color": "00000000"
    },
    {
      "cell": "B6",
      "value": "(1-R2-R3) x Ed",
      "color": "00000000"
    },
    {
      "cell": "A8",
      "value": "Full Circular Footprint Formula (F-CFF) ",
      "color": "00000000"
    },
    {
      "cell": "A9",
      "value": "E= (1-R1) x Ev + R1 x (A x Erin + (1-A) x Ev x Qsin/Qp) + (1-A) x R2 x (Eout - Ev* x (QSout/QP)+ (1-B) x R3 x (Eer - LHV x Xerheat x Eseheat - LHV x Xerelec x Eseelec) + (1-R2-R3) x Ed ",
      "color": "00000000"
    },
    {
      "cell": "K10",
      "value": "Factor A",
      "color": "00000000"
    },
    {
      "cell": "L10",
      "value": "0.5",
      "color": "00000000"
    },
    {
      "cell": "M10",
      "value": "A balance between supply and demand for recycled material [0.2-0.8]",
      "color": "00000000"
    },
    {
      "cell": "K11",
      "value": "Ed",
      "color": "00000000"
    },
    {
      "cell": "L11",
      "value": "0.4903",
      "color": "00000000"
    },
    {
      "cell": "M11",
      "value": "is the environmental burdens of the waste disposal",
      "color": "00000000"
    },
    {
      "cell": "B12",
      "value": "=((1-$L$24)*$L$25)*VLOOKUP(EngS_BioCalc!E33,'Dados auxiliares'!B7:H12,7,0)-(VLOOKUP(EngS_BioCalc!E33,'Dados auxiliares'!B7:H12,7,0)*L29*L30)-(VLOOKUP(EngS_BioCalc!E33,'Dados auxiliares'!B7:H12,7,0)*L31*L32)",
      "color": "00000000"
    },
    {
      "cell": "D12",
      "value": "=EngS_BioCalc!C21+B12",
      "color": "00000000"
    },
    {
      "cell": "K12",
      "value": "Ed*",
      "color": "00000000"
    },
    {
      "cell": "M12",
      "value": "indicates Ed is avoided through recycling",
      "color": "00000000"
    },
    {
      "cell": "K13",
      "value": "Erin",
      "color": "00000000"
    },
    {
      "cell": "L13",
      "value": "0.0",
      "color": "00000000"
    },
    {
      "cell": "M13",
      "value": "is the environmental burdens of the recycling process supplying recycled material to the product",
      "color": "00000000"
    },
    {
      "cell": "K14",
      "value": "Erout",
      "color": "00000000"
    },
    {
      "cell": "L14",
      "value": "0.0",
      "color": "00000000"
    },
    {
      "cell": "M14",
      "value": "is the environmental burdens of the recycling process accepting materials from the produc",
      "color": "00000000"
    },
    {
      "cell": "K15",
      "value": "Ev",
      "color": "00000000"
    },
    {
      "cell": "L15",
      "value": "0.0",
      "color": "00000000"
    },
    {
      "cell": "M15",
      "value": "is the environmental burdens of virgin material production",
      "color": "00000000"
    },
    {
      "cell": "K16",
      "value": "Ev*",
      "color": "00000000"
    },
    {
      "cell": "L16",
      "value": "0.0",
      "color": "00000000"
    },
    {
      "cell": "M16",
      "value": "indicates Ev is avoided through recycling",
      "color": "00000000"
    },
    {
      "cell": "K17",
      "value": "R1",
      "color": "00000000"
    },
    {
      "cell": "L17",
      "value": "0.0",
      "color": "00000000"
    },
    {
      "cell": "M17",
      "value": "Share of recycled material [0-1]",
      "color": "00000000"
    },
    {
      "cell": "K18",
      "value": "R2",
      "color": "00000000"
    },
    {
      "cell": "L18",
      "value": "0.0",
      "color": "00000000"
    },
    {
      "cell": "M18",
      "value": "the rate of recycling of material after use in the product [0-1]",
      "color": "00000000"
    },
    {
      "cell": "K19",
      "value": "Qp",
      "color": "00000000"
    },
    {
      "cell": "L19",
      "value": "1.0",
      "color": "00000000"
    },
    {
      "cell": "M19",
      "value": "is the quality of the material delivered by the primary production [0-1]",
      "color": "00000000"
    },
    {
      "cell": "K20",
      "value": "Qs",
      "color": "00000000"
    },
    {
      "cell": "L20",
      "value": "1.0",
      "color": "00000000"
    },
    {
      "cell": "M20",
      "value": "quality of material recycled from the investigated product [0-1]",
      "color": "00000000"
    },
    {
      "cell": "K21",
      "value": "Qsin",
      "color": "00000000"
    },
    {
      "cell": "L21",
      "value": "1.0",
      "color": "00000000"
    },
    {
      "cell": "M21",
      "value": "the quality of recycled material entering the life cycle [0-1]",
      "color": "00000000"
    },
    {
      "cell": "K22",
      "value": "Qsout",
      "color": "00000000"
    },
    {
      "cell": "L22",
      "value": "0.0",
      "color": "00000000"
    },
    {
      "cell": "M22",
      "value": "the quality of recycled material leaving the life cycle [0-1]",
      "color": "00000000"
    },
    {
      "cell": "K23",
      "value": "S",
      "color": "00000000"
    },
    {
      "cell": "L23",
      "value": "1.0",
      "color": "00000000"
    },
    {
      "cell": "M23",
      "value": "the quality of the recycled material divided by the quality of virgin material [0-1]",
      "color": "00000000"
    },
    {
      "cell": "K24",
      "value": "B",
      "color": "00000000"
    },
    {
      "cell": "L24",
      "value": "0.0",
      "color": "00000000"
    },
    {
      "cell": "M24",
      "value": "allocation factor of energy recovery processes: it applies both to burdens and credits - Equalqs to 0 as default",
      "color": "00000000"
    },
    {
      "cell": "K25",
      "value": "R3",
      "color": "00000000"
    },
    {
      "cell": "L25",
      "value": "1.0",
      "color": "00000000"
    },
    {
      "cell": "M25",
      "value": "it is the proportion of the material in the product that is used for energy recovery at EoL",
      "color": "00000000"
    },
    {
      "cell": "K26",
      "value": "Eer",
      "color": "00000000"
    },
    {
      "cell": "L26",
      "value": "0.0",
      "color": "00000000"
    },
    {
      "cell": "M26",
      "value": "specific emissions and resources consumed (per functional unit) arising from the energy recovery process (e.g. incineration with energy recovery, landfill with energy recovery, …)",
      "color": "00000000"
    },
    {
      "cell": "K27",
      "value": "LHV (Biomass)",
      "color": "00000000"
    },
    {
      "cell": "L27",
      "value": "12.1417",
      "color": "00000000"
    },
    {
      "cell": "M27",
      "value": "lower heating value for Biomass[MJ/kg]",
      "color": "00000000"
    },
    {
      "cell": "K28",
      "value": "LHV (Biofuel)",
      "color": "00000000"
    },
    {
      "cell": "L28",
      "value": "6.1852",
      "color": "00000000"
    },
    {
      "cell": "M28",
      "value": "lower heating value for densified Biofuel[MJ/kg]",
      "color": "00000000"
    },
    {
      "cell": "K29",
      "value": "Xerheat",
      "color": "00000000"
    },
    {
      "cell": "L29",
      "value": "1.0",
      "color": "00000000"
    },
    {
      "cell": "M29",
      "value": "the efficiency of the energy recovery process for heat",
      "color": "00000000"
    },
    {
      "cell": "K30",
      "value": "Eseheat (GWP)",
      "color": "00000000"
    },
    {
      "cell": "L30",
      "value": "0.85",
      "color": "00000000"
    },
    {
      "cell": "M30",
      "value": "specific emissions and resources consumed (per functional unit) that would have arisen from the specific substituted energy source. For this case, heat",
      "color": "00000000"
    },
    {
      "cell": "AD30",
      "value": "Eseheat (Impact/MJ) =  results (per MJ of Eucalyptus) / LHV (Briquettes) ",
      "color": "00000000"
    },
    {
      "cell": "K31",
      "value": "Xerelec",
      "color": "00000000"
    },
    {
      "cell": "L31",
      "value": "0.0",
      "color": "00000000"
    },
    {
      "cell": "M31",
      "value": "the efficiency of the energy recovery process for elec",
      "color": "00000000"
    },
    {
      "cell": "K32",
      "value": "Eseelec",
      "color": "00000000"
    },
    {
      "cell": "L32",
      "value": "0.35",
      "color": "00000000"
    },
    {
      "cell": "M32",
      "value": "specific emissions and resources consumed (per functional unit) that would have arisen from the specific substituted energy source. For this case, electricity",
      "color": "00000000"
    },
    {
      "cell": "P36",
      "value": "Xerheat",
      "color": "00000000"
    },
    {
      "cell": "Q36",
      "value": "1.0",
      "color": "00000000"
    },
    {
      "cell": "P37",
      "value": "Eseheat (GWP)",
      "color": "00000000"
    },
    {
      "cell": "K38",
      "value": "Xerheat",
      "color": "00000000"
    },
    {
      "cell": "L38",
      "value": "1.0",
      "color": "00000000"
    },
    {
      "cell": "P38",
      "value": "Xerelec",
      "color": "00000000"
    },
    {
      "cell": "Q38",
      "value": "1.0",
      "color": "00000000"
    },
    {
      "cell": "K39",
      "value": "Eseheat (GWP)",
      "color": "00000000"
    },
    {
      "cell": "L39",
      "value": "0.85",
      "color": "00000000"
    },
    {
      "cell": "P39",
      "value": "Eseelec",
      "color": "00000000"
    },
    {
      "cell": "Q39",
      "value": "0.0",
      "color": "00000000"
    },
    {
      "cell": "K40",
      "value": "Xerelec",
      "color": "00000000"
    },
    {
      "cell": "L40",
      "value": "0.0",
      "color": "00000000"
    },
    {
      "cell": "K41",
      "value": "Eseelec",
      "color": "00000000"
    },
    {
      "cell": "L41",
      "value": "0.35",
      "color": "00000000"
    }
  ]
}